PygameUtils/__init__.py
PygameUtils/button.py
PygameUtils/checkbox.py
utils_pygame-0.0.1.dist-info/LICENSE
utils_pygame-0.0.1.dist-info/METADATA
utils_pygame-0.0.1.dist-info/WHEEL
utils_pygame-0.0.1.dist-info/top_level.txt
utils_pygame-0.0.1.dist-info/RECORD
