Metadata-Version: 2.1
Name: utils-pygame
Version: 0.0.1
Summary: A compilation of utility tools for pygame
Home-page: https://github.com/tiagofneto/pygame-utils
Author: Tiago Neto
Author-email: tiago.f.neto@gmail.com
License: MIT
Platform: UNKNOWN
Classifier: Development Status :: 3 - Alpha
Classifier: Intended Audience :: Developers
Classifier: Programming Language :: Python :: 3
Classifier: License :: OSI Approved :: MIT License
Classifier: Operating System :: OS Independent
